remedian/__init__.py
remedian/remedian.py
remedian-0.1.2.dist-info/LICENSE
remedian-0.1.2.dist-info/METADATA
remedian-0.1.2.dist-info/WHEEL
remedian-0.1.2.dist-info/top_level.txt
remedian-0.1.2.dist-info/RECORD
