Metadata-Version: 2.1
Name: remedian
Version: 0.1.2
Summary: Remedian: robust averaging of large data sets
Home-page: http://github.com/sappelhoff/remedian
Author: Stefan Appelhoff
Author-email: stefan.appelhoff@mailbox.org
License: MIT
Project-URL: Bug Reports, https://github.com/sappelhoff/remedian/issues
Project-URL: Source, https://github.com/sappelhoff/remedian
Keywords: remedian median memory efficient big data
Platform: UNKNOWN
Classifier: Topic :: Scientific/Engineering :: Mathematics
Classifier: Programming Language :: Python
Classifier: License :: OSI Approved :: MIT License
Classifier: Intended Audience :: Science/Research
Requires-Python: >=2.7
Requires-Dist: numpy (>=1.14.1)
Provides-Extra: test
Requires-Dist: pytest (>=3.6) ; extra == 'test'
Requires-Dist: pytest-cov ; extra == 'test'
